exasol/pytest_slc/__init__.py
exasol/pytest_slc/py.typed
exasol/pytest_slc/version.py
pytest_exasol_slc-0.4.3.dist-info/METADATA
pytest_exasol_slc-0.4.3.dist-info/WHEEL
pytest_exasol_slc-0.4.3.dist-info/entry_points.txt
pytest_exasol_slc-0.4.3.dist-info/RECORD
